[
  {
    "Type": "BlueprintGeneratedClass",
    "Name": "GE_Consumable_BuildingCost_C",
    "Class": "UScriptClass'BlueprintGeneratedClass'",
    "SuperStruct": {
      "ObjectName": "Class'GameplayEffect'",
      "ObjectPath": "/Script/GameplayAbilities"
    },
    "ClassFlags": "CLASS_Optional | CLASS_CompiledFromBlueprint | CLASS_HasInstancedReference",
    "ClassWithin": {
      "ObjectName": "Class'Object'",
      "ObjectPath": "/Script/CoreUObject"
    },
    "ClassConfigName": "Engine",
    "bCooked": true,
    "ClassDefaultObject": {
      "ObjectName": "GE_Consumable_BuildingCost_C'Default__GE_Consumable_BuildingCost_C'",
      "ObjectPath": "FortniteGame/Content/Loot/Consumables/GameplayEffects/GE_Consumable_BuildingCost.1"
    }
  },
  {
    "Type": "GE_Consumable_BuildingCost_C",
    "Name": "Default__GE_Consumable_BuildingCost_C",
    "Class": "BlueprintGeneratedClass'FortniteGame/Content/Loot/Consumables/GameplayEffects/GE_Consumable_BuildingCost.GE_Consumable_BuildingCost_C'",
    "Properties": {
      "DurationPolicy": "EGameplayEffectDurationType::HasDuration",
      "DurationMagnitude": {
        "ScalableFloatMagnitude": {
          "Value": 9.0
        }
      },
      "Modifiers": [
        {
          "Attribute": {
            "Attribute": {
              "ObjectName": "FloatProperty'FortConstructionSet:BuildCost'",
              "ObjectPath": "/Script/FortniteGame"
            }
          },
          "ModifierOp": "EGameplayModOp::Multiplicitive",
          "Magnitude": {
            "Value": 0.0,
            "Curve": {
              "CurveTable": null,
              "RowName": "None"
            }
          },
          "ModifierMagnitude": {
            "MagnitudeCalculationType": "EGameplayEffectMagnitudeCalculation::ScalableFloat",
            "ScalableFloatMagnitude": {
              "Value": 1.0,
              "Curve": {
                "CurveTable": {
                  "ObjectName": "CurveTable'Consumables'",
                  "ObjectPath": "FortniteGame/Content/Balance/DataTables/Consumables.0"
                },
                "RowName": "Buff_BuildingCost"
              }
            },
            "AttributeBasedMagnitude": {
              "Coefficient": {
                "Value": 1.0,
                "Curve": {
                  "CurveTable": {
                    "ObjectName": "CurveTable'Consumables'",
                    "ObjectPath": "FortniteGame/Content/Balance/DataTables/Consumables.0"
                  },
                  "RowName": "Buff_BuildingCost"
                }
              },
              "PreMultiplyAdditiveValue": {
                "Value": 0.0,
                "Curve": {
                  "CurveTable": null,
                  "RowName": "None"
                }
              },
              "PostMultiplyAdditiveValue": {
                "Value": 0.0,
                "Curve": {
                  "CurveTable": null,
                  "RowName": "None"
                }
              },
              "BackingAttribute": {
                "AttributeToCapture": {
                  "Attribute": {
                    "ObjectName": "FloatProperty'FortConstructionSet:BuildCost'",
                    "ObjectPath": "/Script/FortniteGame"
                  }
                },
                "AttributeSource": "EGameplayEffectAttributeCaptureSource::Source",
                "bSnapshot": true
              },
              "AttributeCurve": {
                "CurveTable": null,
                "RowName": "None"
              },
              "AttributeCalculationType": "EAttributeBasedFloatCalculationType::AttributeMagnitude",
              "SourceTagFilter": [],
              "TargetTagFilter": []
            },
            "CustomMagnitude": {
              "CalculationClassMagnitude": null,
              "Coefficient": {
                "Value": 1.0,
                "Curve": {
                  "CurveTable": null,
                  "RowName": "None"
                }
              },
              "PreMultiplyAdditiveValue": {
                "Value": 0.0,
                "Curve": {
                  "CurveTable": null,
                  "RowName": "None"
                }
              },
              "PostMultiplyAdditiveValue": {
                "Value": 0.0,
                "Curve": {
                  "CurveTable": null,
                  "RowName": "None"
                }
              }
            },
            "SetByCallerMagnitude": {
              "DataName": "None"
            }
          },
          "SourceTags": {
            "RequireTags": [],
            "IgnoreTags": []
          },
          "TargetTags": {
            "RequireTags": [],
            "IgnoreTags": []
          }
        }
      ],
      "StackingType": "EGameplayEffectStackingType::AggregateBySource",
      "StackLimitCount": 1
    }
  }
]