[
  {
    "Type": "FortSchematicItemDefinition",
    "Name": "Assault_Burst_T04",
    "Class": "UScriptClass'FortSchematicItemDefinition'",
    "Properties": {
      "Requirements": [
        {
          "ItemDefinition": {
            "ObjectName": "FortIngredientItemDefinition'Ingredient_Nuts_Bolts'",
            "ObjectPath": "FortniteGame/Content/Loot/Ingredients/Ingredient_Nuts_Bolts.0"
          },
          "Count": 20,
          "bIsConsumed": true
        },
        {
          "ItemDefinition": {
            "ObjectName": "FortIngredientItemDefinition'Ingredient_Mechanical_Parts'",
            "ObjectPath": "FortniteGame/Content/Loot/Ingredients/Ingredient_Mechanical_Parts.0"
          },
          "Count": 13,
          "bIsConsumed": true
        },
        {
          "ItemDefinition": {
            "ObjectName": "FortIngredientItemDefinition'Ingredient_Ore_Copper'",
            "ObjectPath": "FortniteGame/Content/Loot/Ingredients/Ingredient_Ore_Copper.0"
          },
          "Count": 7,
          "bIsConsumed": true
        },
        {
          "ItemDefinition": {
            "ObjectName": "FortIngredientItemDefinition'Ingredient_Duct_Tape'",
            "ObjectPath": "FortniteGame/Content/Loot/Ingredients/Ingredient_Duct_Tape.0"
          },
          "Count": 1,
          "bIsConsumed": true
        }
      ],
      "Result": {
        "ObjectName": "FortWeaponRangedItemDefinition'Assault_Burst_T04'",
        "ObjectPath": "FortniteGame/Content/Weapons/WeaponItemData/Assault/Assault_Burst_T04.0"
      },
      "CraftingPoints": 780,
      "LootLevelData": {
        "DataTable": {
          "ObjectName": "DataTable'LootLevelData'",
          "ObjectPath": "FortniteGame/Content/Loot/DataTables/LootLevelData.0"
        },
        "ColumnName": "Category",
        "RowContents": "crafting"
      },
      "LevelToXpHandle": {
        "CurveTable": {
          "ObjectName": "CurveTable'XPAccountItemLevels'",
          "ObjectPath": "FortniteGame/Content/Balance/DataTables/XPAccountItemLevels.0"
        },
        "RowName": "4_Common"
      },
      "LevelToSacrificeXpHandle": {
        "CurveTable": {
          "ObjectName": "CurveTable'XPAccountItemRewards'",
          "ObjectPath": "FortniteGame/Content/Balance/DataTables/XPAccountItemRewards.0"
        },
        "RowName": "4_Common"
      },
      "MaxLevel": 5,
      "GameplayTags": [
        "Weapon.Ranged.assault"
      ],
      "AttributeTemplate": "/Game/Loot/Schematics/SchematicAttributeTemplate.SchematicAttributeTemplate",
      "IconBrush": {
        "ResourceObject": {
          "ObjectName": "Texture2D'EditorIcon-Atlas-Grey'",
          "ObjectPath": "FortniteGame/Content/UI/Icons/EditorIcon-Atlas-Grey.0"
        }
      },
      "Rarity": "EFortRarity::Quality"
    }
  }
]