[
  {
    "Type": "FortQuestItemDefinition",
    "Name": "OutpostQuest_T2_L2",
    "Class": "UScriptClass'FortQuestItemDefinition'",
    "Properties": {
      "Rewards": [
        {
          "ItemDefinition": "/Game/Quests/Outpost/Outpost_Filler_Plankerton_D2.Outpost_Filler_Plankerton_D2",
          "Quantity": 1
        },
        {
          "ItemDefinition": "/Game/Loot/PersistentResources/ConstructionPlans_Class.ConstructionPlans_Class",
          "Quantity": 1
        }
      ],
      "Objectives": [
        {
          "ObjectiveStatHandle": {
            "DataTable": {
              "ObjectName": "DataTable'ObjectiveStatTable'",
              "ObjectPath": "FortniteGame/Content/Quests/ObjectiveStatTable.0"
            },
            "RowName": "complete_outpost_2_2"
          },
          "AlternativeStatHandles": [],
          "Description": {
            "CultureInvariantString": null
          },
          "Count": 1,
          "ScriptedAction": ""
        }
      ],
      "Category": {
        "DataTable": {
          "ObjectName": "DataTable'QuestCategoryTable'",
          "ObjectPath": "FortniteGame/Content/Quests/QuestCategoryTable.0"
        },
        "RowName": "Outpost"
      },
      "RewardDescription": {
        "Namespace": "",
        "Key": "961C25BF4845E2D61B0510B0CD7EACBA",
        "SourceString": "Hero Building Plans",
        "LocalizedString": "Hero Building Plans"
      },
      "MissionConfigMetadata": {
        "ConfigParams": [
          {
            "Tag": {
              "TagName": "Quest.Metadata.Mission.Primary.Outpost"
            },
            "ConfigDataClass": "/Game/Quests/Outpost/MIssionMetadata/OutpostQuestMissionData_L2.OutpostQuestMissionData_L2_C"
          }
        ]
      },
      "DisplayName": {
        "Namespace": "",
        "Key": "DAF954504E3CBF1D9F65169A34AC80AF",
        "SourceString": "Expand Plankerton Outpost",
        "LocalizedString": "Expand Plankerton Outpost"
      },
      "Description": {
        "Namespace": "",
        "Key": "655139D4411D500A7CE3B094B9238C40",
        "SourceString": "Install and Defend the first Storm Shield Amplifier",
        "LocalizedString": "Install and Defend the first Storm Shield Amplifier"
      },
      "IconBrush": {
        "ImageSize": {
          "X": 104.0,
          "Y": 104.0
        },
        "ResourceObject": {
          "ObjectName": "Texture2D'Icon-Quest-Outpost-XL'",
          "ObjectPath": "FortniteGame/Content/UI/Icons/Icon-QuestCategory/Icon-Quest-Outpost-XL.0"
        }
      },
      "MultiSizeIconBrush": {
        "Brush_XXS": {
          "ImageSize": {
            "X": 12.0,
            "Y": 12.0
          },
          "ResourceObject": {
            "ObjectName": "Texture2D'Icon-Quest-Outpost-S'",
            "ObjectPath": "FortniteGame/Content/UI/Icons/Icon-QuestCategory/Icon-Quest-Outpost-S.0"
          }
        },
        "Brush_XS": {
          "ImageSize": {
            "X": 16.0,
            "Y": 16.0
          },
          "ResourceObject": {
            "ObjectName": "Texture2D'Icon-Quest-Outpost-S'",
            "ObjectPath": "FortniteGame/Content/UI/Icons/Icon-QuestCategory/Icon-Quest-Outpost-S.0"
          }
        },
        "Brush_S": {
          "ImageSize": {
            "X": 24.0,
            "Y": 24.0
          },
          "ResourceObject": {
            "ObjectName": "Texture2D'Icon-Quest-Outpost-S'",
            "ObjectPath": "FortniteGame/Content/UI/Icons/Icon-QuestCategory/Icon-Quest-Outpost-S.0"
          }
        },
        "Brush_M": {
          "ImageSize": {
            "X": 40.0,
            "Y": 40.0
          },
          "ResourceObject": {
            "ObjectName": "Texture2D'Icon-Quest-Outpost-M'",
            "ObjectPath": "FortniteGame/Content/UI/Icons/Icon-QuestCategory/Icon-Quest-Outpost-M.0"
          }
        },
        "Brush_L": {
          "ImageSize": {
            "X": 64.0,
            "Y": 64.0
          },
          "ResourceObject": {
            "ObjectName": "Texture2D'Icon-Quest-Outpost-L'",
            "ObjectPath": "FortniteGame/Content/UI/Icons/Icon-QuestCategory/Icon-Quest-Outpost-L.0"
          }
        },
        "Brush_XL": {
          "ImageSize": {
            "X": 104.0,
            "Y": 104.0
          },
          "ResourceObject": {
            "ObjectName": "Texture2D'Icon-Quest-Outpost-XL'",
            "ObjectPath": "FortniteGame/Content/UI/Icons/Icon-QuestCategory/Icon-Quest-Outpost-XL.0"
          }
        }
      }
    }
  }
]