[
  {
    "Type": "FortQuestItemDefinition",
    "Name": "OutpostQuest_T3_L4",
    "Class": "UScriptClass'FortQuestItemDefinition'",
    "Properties": {
      "Rewards": [
        {
          "ItemDefinition": "/Game/Quests/Outpost/Outpost_Filler_Canny_D4.Outpost_Filler_Canny_D4",
          "Quantity": 1
        },
        {
          "ItemDefinition": "/Game/Loot/PersistentResources/UpgradePlans.UpgradePlans",
          "Quantity": 1
        }
      ],
      "Objectives": [
        {
          "ObjectiveStatHandle": {
            "DataTable": {
              "ObjectName": "DataTable'ObjectiveStatTable'",
              "ObjectPath": "FortniteGame/Content/Quests/ObjectiveStatTable.0"
            },
            "RowName": "complete_outpost_3_4"
          },
          "AlternativeStatHandles": [],
          "Description": {
            "CultureInvariantString": null
          },
          "Count": 1,
          "ScriptedAction": ""
        }
      ],
      "Category": {
        "DataTable": {
          "ObjectName": "DataTable'QuestCategoryTable'",
          "ObjectPath": "FortniteGame/Content/Quests/QuestCategoryTable.0"
        },
        "RowName": "Outpost"
      },
      "RewardDescription": {
        "Namespace": "",
        "Key": "926E983C4509A96F46EB889E902D4886",
        "SourceString": "Home Base Upgrade Plans",
        "LocalizedString": "Home Base Upgrade Plans"
      },
      "MissionConfigMetadata": {
        "ConfigParams": [
          {
            "Tag": {
              "TagName": "Quest.Metadata.Mission.Primary.Outpost"
            },
            "ConfigDataClass": "/Game/Quests/Outpost/MIssionMetadata/OutpostQuestMissionData_L4.OutpostQuestMissionData_L4_C"
          }
        ]
      },
      "DisplayName": {
        "Namespace": "",
        "Key": "58BBE70947E6ED76EE749484A36C60D9",
        "SourceString": "Expand Canny Valley Outpost",
        "LocalizedString": "Expand Canny Valley Outpost"
      },
      "Description": {
        "Namespace": "",
        "Key": "C2644BDA43BC8CB0DADD57831D17A2E2",
        "SourceString": "Install and Defend the third Storm Shield Amplifier",
        "LocalizedString": "Install and Defend the third Storm Shield Amplifier"
      },
      "IconBrush": {
        "ImageSize": {
          "X": 104.0,
          "Y": 104.0
        },
        "ResourceObject": {
          "ObjectName": "Texture2D'Icon-Quest-Outpost-XL'",
          "ObjectPath": "FortniteGame/Content/UI/Icons/Icon-QuestCategory/Icon-Quest-Outpost-XL.0"
        }
      },
      "MultiSizeIconBrush": {
        "Brush_XXS": {
          "ImageSize": {
            "X": 12.0,
            "Y": 12.0
          },
          "ResourceObject": {
            "ObjectName": "Texture2D'Icon-Quest-Outpost-S'",
            "ObjectPath": "FortniteGame/Content/UI/Icons/Icon-QuestCategory/Icon-Quest-Outpost-S.0"
          }
        },
        "Brush_XS": {
          "ImageSize": {
            "X": 16.0,
            "Y": 16.0
          },
          "ResourceObject": {
            "ObjectName": "Texture2D'Icon-Quest-Outpost-S'",
            "ObjectPath": "FortniteGame/Content/UI/Icons/Icon-QuestCategory/Icon-Quest-Outpost-S.0"
          }
        },
        "Brush_S": {
          "ImageSize": {
            "X": 24.0,
            "Y": 24.0
          },
          "ResourceObject": {
            "ObjectName": "Texture2D'Icon-Quest-Outpost-S'",
            "ObjectPath": "FortniteGame/Content/UI/Icons/Icon-QuestCategory/Icon-Quest-Outpost-S.0"
          }
        },
        "Brush_M": {
          "ImageSize": {
            "X": 40.0,
            "Y": 40.0
          },
          "ResourceObject": {
            "ObjectName": "Texture2D'Icon-Quest-Outpost-M'",
            "ObjectPath": "FortniteGame/Content/UI/Icons/Icon-QuestCategory/Icon-Quest-Outpost-M.0"
          }
        },
        "Brush_L": {
          "ImageSize": {
            "X": 64.0,
            "Y": 64.0
          },
          "ResourceObject": {
            "ObjectName": "Texture2D'Icon-Quest-Outpost-L'",
            "ObjectPath": "FortniteGame/Content/UI/Icons/Icon-QuestCategory/Icon-Quest-Outpost-L.0"
          }
        },
        "Brush_XL": {
          "ImageSize": {
            "X": 104.0,
            "Y": 104.0
          },
          "ResourceObject": {
            "ObjectName": "Texture2D'Icon-Quest-Outpost-XL'",
            "ObjectPath": "FortniteGame/Content/UI/Icons/Icon-QuestCategory/Icon-Quest-Outpost-XL.0"
          }
        }
      }
    }
  }
]